dbso/__init__.py
dbso/connect.py
dbso/database.py
dbso/table.py
dbso/core/__init__.py
dbso/core/colum.py
dbso/core/condition.py
dbso/core/so.py
dbso/core/tool.py
dbso/word/__init__.py
dbso/word/charset.py
dbso/word/datatype.py
dbso/word/engine.py
dbso-1.1.0.dist-info/LICENSE
dbso-1.1.0.dist-info/METADATA
dbso-1.1.0.dist-info/WHEEL
dbso-1.1.0.dist-info/top_level.txt
dbso-1.1.0.dist-info/RECORD
