Metadata-Version: 2.1
Name: dbso
Version: 1.1.0
Summary: A object-oriented way to manage SQL databases with Python’s library
Home-page: https://github.com/ninecoding/dbso
Author: Nine
Author-email: ninecodespace@gamil.com
License: GPL version 3
Platform: UNKNOWN
Classifier: Programming Language :: Python :: 3
Classifier: Operating System :: OS Independent
Requires-Python: >=3.6
License-File: LICENSE
